neuroseg/__init__.py
neuroseg/core/__init__.py
neuroseg/core/predictor.py
neuroseg/core/predictor_multilabel.py
neuroseg/core/trainer.py
neuroseg/datasets/__init__.py
neuroseg/datasets/dataset.py
neuroseg/datasets/datatypes.py
neuroseg/datasets/filetypes.py
neuroseg/datasets/specification.py
neuroseg/nets/RSUNet.py
neuroseg/nets/RSUNetMulti.py
neuroseg/nets/__init__.py
neuroseg/nets/layers.py
neuroseg/nets/netcollector.py
neuroseg/training/__init__.py
neuroseg/training/checkpoint.py
neuroseg/training/logging.py
tests/__init__.py
tests/test_augmentations.py
tests/test_core.py
tests/test_dataset.py
tests/test_net.py
tests/test_reconstruction.py
neuroseg-0.1.2.dist-info/LICENSE
neuroseg-0.1.2.dist-info/METADATA
neuroseg-0.1.2.dist-info/WHEEL
neuroseg-0.1.2.dist-info/top_level.txt
neuroseg-0.1.2.dist-info/RECORD
