Metadata-Version: 2.1
Name: neuroseg
Version: 0.1.2
Summary: A PyTorch-based framework for deep learning in neuroscience
Author: Allen Institute for Brain Science
License-File: LICENSE
Requires-Dist: numpy >=1.14.5
Requires-Dist: tensorboardX >=1.2
Requires-Dist: torch ==1.13.1
Requires-Dist: tifffile ==2023.1.23.1
Requires-Dist: h5py >=2.7.1
Requires-Dist: scipy >=1.1.0
Requires-Dist: pybind11 >=2.2.3
Requires-Dist: psutil >=5.4.7
